ChangeLog
INSTALL
MANIFEST.in
Makefile
README
python-psys.spec
setup.py
psys/__init__.py
psys/daemon.py
psys/pipe.py
psys/poll.py
psys/process.py
psys.egg-info/PKG-INFO
psys.egg-info/SOURCES.txt
psys.egg-info/dependency_links.txt
psys.egg-info/requires.txt
psys.egg-info/top_level.txt