Metadata-Version: 1.1
Name: psys
Version: 0.4.1
Summary: A Python module with a set of basic tools for writing system utilities
Home-page: http://github.com/KonishchevDmitry/psys
Author: Dmitry Konishchev
Author-email: konishchev@gmail.com
License: MIT
Platform: unix
Platform: linux
Platform: osx
Classifier: Development Status :: 4 - Beta
Classifier: Intended Audience :: Developers
Classifier: License :: OSI Approved :: MIT License
Classifier: Operating System :: MacOS :: MacOS X
Classifier: Operating System :: POSIX
Classifier: Operating System :: Unix
Classifier: Programming Language :: Python :: 2
Classifier: Programming Language :: Python :: 3
Classifier: Topic :: Software Development :: Libraries :: Python Modules
